{
  "$schema": "https://biomejs.dev/schemas/2.4.10/schema.json",
  "vcs": {
    "enabled": true,
    "clientKind": "git",
    "useIgnoreFile": true
  },
  "files": {
    "ignoreUnknown": true,
    "includes": ["**/*.ts", "**/*.js", "**/*.mjs", "**/*.mts", "**/*.json"]
  },
  "formatter": {
    "enabled": true,
    "indentStyle": "space",
    "indentWidth": 2,
    "lineWidth": 100,
    "lineEnding": "lf"
  },
  "linter": {
    "enabled": true,
    "rules": {
      "recommended": true,
      "style": {
        "noNonNullAssertion": "off",
        "useImportType": "warn",
        "noUnusedTemplateLiteral": "off"
      },
      "suspicious": {
        "noExplicitAny": "warn"
      },
      "correctness": {
        "noUnusedVariables": "warn",
        "noUnusedImports": "warn"
      }
    }
  },
  "javascript": {
    "formatter": {
      "quoteStyle": "double",
      "jsxQuoteStyle": "double",
      "semicolons": "always",
      "trailingCommas": "all",
      "arrowParentheses": "always"
    }
  },
  "json": {
    "formatter": {
      "enabled": true,
      "indentStyle": "space",
      "indentWidth": 2
    }
  },
  "assist": {
    "enabled": true,
    "actions": {
      "source": {
        "organizeImports": "on"
      }
    }
  },
  "overrides": [
    {
      "includes": [
        "**/*.test.ts",
        "**/*.test.tsx",
        "**/*.spec.ts",
        "**/__tests__/**",
        "**/tests/**"
      ],
      "linter": {
        "rules": {
          "suspicious": {
            "noExplicitAny": "off"
          },
          "performance": {
            "noDelete": "off"
          }
        }
      }
    },
    {
      "includes": ["**/scripts/**"],
      "linter": {
        "enabled": false
      }
    }
  ]
}
